ditts/__init__.py
ditts/accents.py
ditts/cli.py
ditts/lang.py
ditts/langs.py
ditts/tts.py
ditts/utils.py
ditts/version.py
ditts/tests/__init__.py
ditts/tests/test_cli.py
ditts/tests/test_lang.py
ditts/tests/test_tts.py
ditts/tests/test_utils.py
ditts/tokenizer/__init__.py
ditts/tokenizer/core.py
ditts/tokenizer/pre_processors.py
ditts/tokenizer/symbols.py
ditts/tokenizer/tokenizer_cases.py
diTTS-2.6.7.dist-info/LICENSE
diTTS-2.6.7.dist-info/METADATA
diTTS-2.6.7.dist-info/WHEEL
diTTS-2.6.7.dist-info/entry_points.txt
diTTS-2.6.7.dist-info/top_level.txt
diTTS-2.6.7.dist-info/RECORD
