Metadata-Version: 2.1
Name: diTTS
Version: 2.6.7
Summary: diTTS (Google Text-to-Speech), a Python library and CLI tool to interface with Google Translate text-to-speech API
Home-page: https://github.com/blket.dev/diTTS
Author: blket.dev
Author-email: blket.dev@gmail.com
License: MIT
Keywords: ditts,text to speech,NAVER Papago,TTS
Classifier: Environment :: Console
Classifier: Intended Audience :: Developers
Classifier: License :: OSI Approved :: MIT License
Classifier: Operating System :: MacOS
Classifier: Operating System :: Unix
Classifier: Operating System :: POSIX
Classifier: Operating System :: POSIX :: Linux
Classifier: Operating System :: Microsoft :: Windows
Classifier: Programming Language :: Python :: 3.8
Classifier: Programming Language :: Python :: 3.9
Classifier: Programming Language :: Python :: 3.10
Classifier: Programming Language :: Python :: 3.11
Classifier: Programming Language :: Python :: 3.12
Classifier: Topic :: Software Development :: Libraries
Classifier: Topic :: Multimedia :: Sound/Audio :: Speech
Requires-Python: >=3.7
License-File: LICENSE
Requires-Dist: requests <3,>=2.27
Requires-Dist: click <8.2,>=7.1
Provides-Extra: test
Requires-Dist: pytest <8.1.0,>=7.1.3 ; extra == 'test'
Requires-Dist: pytest-cov ; extra == 'test'
Requires-Dist: testfixtures ; extra == 'test'
